dmclient
