Metadata-Version: 1.0
Name: domainmodelclient
Version: 0.4
Summary: Python client for the Domain Model API
Home-page: http://appropriatesoftware.net/domainmodel
Author: Appropriate Software Foundation
Author-email: domainmodel-support@appropriatesoftware.net
License: MIT
Platform: UNKNOWN
Classifier: Development Status :: 4 - Beta
Classifier: Intended Audience :: Developers
Classifier: License :: OSI Approved :: MIT License
Classifier: Operating System :: OS Independent
Classifier: Programming Language :: Python
